Metadata-Version: 2.3
Name: nonebot-plugin-repesix
Version: 0.0.6
Summary: 复读6
License: MIT
Keywords: nonebot,nonebot2,nonebot_plugin,repeat_six
Author: 月ヶ瀬
Requires-Python: >=3.9,<4.0
Classifier: License :: OSI Approved :: MIT License
Classifier: Programming Language :: Python :: 3
Classifier: Programming Language :: Python :: 3.9
Classifier: Programming Language :: Python :: 3.10
Classifier: Programming Language :: Python :: 3.11
Classifier: Programming Language :: Python :: 3.12
Classifier: Programming Language :: Python :: 3.13
Requires-Dist: nonebot2 (>=2.3.1,<3.0.0)
Project-URL: Homepage, https://github.com/tkgs0/nonebot-plugin-repesix
Project-URL: Repository, https://github.com/tkgs0/nonebot-plugin-repesix
